CHANGES.rst
LICENSE
MANIFEST.in
README.rst
setup.cfg
setup.py
Flask_Actions.egg-info/PKG-INFO
Flask_Actions.egg-info/SOURCES.txt
Flask_Actions.egg-info/dependency_links.txt
Flask_Actions.egg-info/namespace_packages.txt
Flask_Actions.egg-info/not-zip-safe
Flask_Actions.egg-info/requires.txt
Flask_Actions.egg-info/top_level.txt
docs/Makefile
docs/conf.py
docs/index.rst
docs/make.bat
docs/_themes/README
docs/_themes/flask_theme_support.py
docs/_themes/flask/theme.conf
docs/_themes/flask/static/flasky.css_t
docs/_themes/flask_small/layout.html
docs/_themes/flask_small/theme.conf
docs/_themes/flask_small/static/flasky.css_t
flaskext/__init__.py
flaskext/actions/__init__.py
flaskext/actions/daemonize.py
flaskext/actions/fastcgi.py
flaskext/actions/flask_admin.py
flaskext/actions/help_actions.py
flaskext/actions/server_actions.py
flaskext/actions/utils.py
flaskext/actions/project_template/__init__.py_tmpl
flaskext/actions/project_template/manage.py_tmpl
flaskext/actions/project_template/settings.py_tmpl
flaskext/actions/project_template/static/style.css
flaskext/actions/project_template/templates/layout.html
flaskext/actions/project_template/views/__init__.py
flaskext/actions/project_template/views/frontend.py
tests/__init__.py