Metadata-Version: 1.0
Name: Flask-Actions
Version: 0.6.1
Summary: custom actions for flask to help manage your application
Home-page: http://blog.flyzen.com
Author: Young King
Author-email: yanckin@gmail.com
License: BSD
Platform: any
Classifier: Development Status :: 4 - Beta
Classifier: Environment :: Web Environment
Classifier: Intended Audience :: Developers
Classifier: License :: OSI Approved :: BSD License
Classifier: Operating System :: OS Independent
Classifier: Programming Language :: Python
Classifier: Topic :: Internet :: WWW/HTTP :: Dynamic Content
Classifier: Topic :: Software Development :: Libraries :: Python Modules
